findsub/__init__.py
findsub/__main__.py
findsub/clean.py
findsub/cli.py
findsub/core/__init__.py
findsub/core/algo.c
findsub/core/algo.pyi
findsub/core/algo.pyx
findsub/data/langs.json
findsub/download.py
findsub/ffmpeg.py
findsub/movie.py
findsub/pycore.py
findsub/pyvideo.py
findsub/scripts/Convert.sh
findsub/subtitles.py
findsub/tools.py
findsub/core/algo.cpython-39-x86_64-linux-gnu.so
findsub-0.7.2.dist-info/entry_points.txt
findsub-0.7.2.dist-info/LICENSE
findsub-0.7.2.dist-info/WHEEL
findsub-0.7.2.dist-info/METADATA
findsub-0.7.2.dist-info/RECORD
